byestore/__init__.py
byestore-0.0.4.dist-info/LICENSE
byestore-0.0.4.dist-info/METADATA
byestore-0.0.4.dist-info/WHEEL
byestore-0.0.4.dist-info/top_level.txt
byestore-0.0.4.dist-info/RECORD
