Metadata-Version: 2.1
Name: byestore
Version: 0.0.4
Summary: A library for ByeStore
Home-page: https://github.com/byestore/byestorelibs
Author: ByeMC
Author-email: byestore@byemc.xyz
License: UNKNOWN
Project-URL: Bug Tracker, https://github.com/byestore/byestorelibs/issues
Platform: UNKNOWN
Classifier: Programming Language :: Python :: 3
Classifier: License :: OSI Approved :: MIT License
Classifier: Operating System :: OS Independent
Classifier: Development Status :: 2 - Pre-Alpha
Classifier: Intended Audience :: Developers
Classifier: Intended Audience :: End Users/Desktop
Classifier: Natural Language :: English
Classifier: Topic :: Internet :: WWW/HTTP
Requires-Python: >=3.6
License-File: LICENSE
